affectlog_erroranalysis/__init__.py
affectlog_erroranalysis/version.py
affectlog_erroranalysis/_internal/__init__.py
affectlog_erroranalysis/_internal/cohort_filter.py
affectlog_erroranalysis/_internal/constants.py
affectlog_erroranalysis/_internal/matrix_filter.py
affectlog_erroranalysis/_internal/metrics.py
affectlog_erroranalysis/_internal/process_categoricals.py
affectlog_erroranalysis/_internal/surrogate_error_tree.py
affectlog_erroranalysis/_internal/utils.py
affectlog_erroranalysis/_internal/version_checker.py
affectlog_erroranalysis/_internal/error_analyzer/__init__.py
affectlog_erroranalysis/_internal/error_report/__init__.py
affectlog_erroranalysis/analyzer/__init__.py
affectlog_erroranalysis/analyzer/error_analyzer.py
affectlog_erroranalysis/error_correlation_methods/__init__.py
affectlog_erroranalysis/error_correlation_methods/ebm.py
affectlog_erroranalysis/error_correlation_methods/gbm.py
affectlog_erroranalysis/report/__init__.py
affectlog_erroranalysis/report/error_report.py
affectlog_erroranalysis-0.5.7.dist-info/LICENSE
affectlog_erroranalysis-0.5.7.dist-info/METADATA
affectlog_erroranalysis-0.5.7.dist-info/WHEEL
affectlog_erroranalysis-0.5.7.dist-info/top_level.txt
affectlog_erroranalysis-0.5.7.dist-info/RECORD
