Metadata-Version: 2.1
Name: affectlog_erroranalysis
Version: 0.5.7
Summary: Core error analysis APIs
Home-page: https://github.com/affectlog/trustworthy-ai-widgets
Author: AL360°
Author-email: developer@affectlog.com
Classifier: Programming Language :: Python :: 3.7
Classifier: Programming Language :: Python :: 3.8
Classifier: Programming Language :: Python :: 3.9
Classifier: Programming Language :: Python :: 3.10
Classifier: Programming Language :: Python :: 3.11
Classifier: License :: OSI Approved :: MIT License
Classifier: Operating System :: OS Independent
Classifier: Development Status :: 3 - Alpha
Requires-Python: >=3.7
License-File: LICENSE
Requires-Dist: numpy<2.0.0,>=1.17.2
Requires-Dist: pandas<2.0.0,>=0.25.1
Requires-Dist: scipy>=1.4.1
Requires-Dist: scikit-learn>=0.22.1
Requires-Dist: lightgbm>=2.0.11
Requires-Dist: affectlog-utils>=0.4.2
Provides-Extra: object_detection
Requires-Dist: vision-explanation-methods; extra == "object-detection"
